a_data_source-0.1.0.dist-info/licenses/LICENSE
data_sources/__init__.py
data_sources/data_source.py
data_sources/errors.py
data_sources/keys.py
data_sources/meta.py
data_sources/registry.py
data_sources/shortcuts.py
data_sources/contrib/__init__.py
data_sources/contrib/django/__init__.py
data_sources/contrib/django/errors.py
data_sources/contrib/django/keys.py
data_sources/contrib/django/shortcuts.py
data_sources/contrib/django/translations.py
data_sources/contrib/django/operations/__init__.py
data_sources/contrib/django/operations/fetch_entities.py
data_sources/contrib/django/operations/queryset.py
data_sources/contrib/django/operations/recursive_data_source.py
data_sources/contrib/django/operations/combine_queryset/__init__.py
data_sources/contrib/django/operations/combine_queryset/combinations.py
data_sources/contrib/django/operations/modify_queryset/__init__.py
data_sources/contrib/django/operations/modify_queryset/as_dicts.py
data_sources/contrib/django/operations/modify_queryset/clear_ordering.py
data_sources/contrib/django/operations/modify_queryset/distinct.py
data_sources/contrib/django/operations/modify_queryset/iterator.py
data_sources/contrib/django/operations/modify_queryset/limit_to_ids.py
data_sources/contrib/django/operations/modify_queryset/limit_to_number.py
data_sources/contrib/django/operations/modify_queryset/values.py
data_sources/contrib/drf/__init__.py
data_sources/contrib/drf/api_view.py
data_sources/contrib/drf/error_hadlers.py
data_sources/contrib/drf/error_handlers.py
data_sources/contrib/drf/errors.py
data_sources/contrib/drf/operations/__init__.py
data_sources/contrib/drf/operations/fetch_params.py
data_sources/contrib/drf/operations/fetch_query_params.py
data_sources/contrib/drf/operations/result_fetcher.py
data_sources/contrib/drf/operations/serialization.py
data_sources/contrib/drf/operations/pagination/__init__.py
data_sources/contrib/drf/operations/pagination/fetch_entities.py
data_sources/contrib/drf/operations/pagination/fetch_params.py
a_data_source-0.1.0.dist-info/METADATA
a_data_source-0.1.0.dist-info/WHEEL
a_data_source-0.1.0.dist-info/top_level.txt
a_data_source-0.1.0.dist-info/RECORD
